qifimanager/__init__.py
qifimanager/manager.py
qifimanager/qifiwebserver.py
qifimanager-1.3.2.dist-info/METADATA
qifimanager-1.3.2.dist-info/RECORD
qifimanager-1.3.2.dist-info/WHEEL
qifimanager-1.3.2.dist-info/entry_points.txt
qifimanager-1.3.2.dist-info/top_level.txt
qifimanager-1.3.2.dist-info/zip-safe
